odoo/addons/mrp_bom_location/README.rst
odoo/addons/mrp_bom_location/__init__.py
odoo/addons/mrp_bom_location/__manifest__.py
odoo/addons/mrp_bom_location/i18n/de.po
odoo/addons/mrp_bom_location/i18n/mrp_bom_location.pot
odoo/addons/mrp_bom_location/models/__init__.py
odoo/addons/mrp_bom_location/models/mrp_bom.py
odoo/addons/mrp_bom_location/readme/CONTRIBUTORS.rst
odoo/addons/mrp_bom_location/readme/DESCRIPTION.rst
odoo/addons/mrp_bom_location/readme/USAGE.rst
odoo/addons/mrp_bom_location/report/__init__.py
odoo/addons/mrp_bom_location/report/bom_structure.py
odoo/addons/mrp_bom_location/static/description/icon.png
odoo/addons/mrp_bom_location/static/description/index.html
odoo/addons/mrp_bom_location/views/mrp_view.xml
odoo/addons/mrp_bom_location/views/report_mrpbomstructure.xml
odoo12_addon_mrp_bom_location-12.0.1.0.2.dist-info/METADATA
odoo12_addon_mrp_bom_location-12.0.1.0.2.dist-info/WHEEL
odoo12_addon_mrp_bom_location-12.0.1.0.2.dist-info/top_level.txt
odoo12_addon_mrp_bom_location-12.0.1.0.2.dist-info/RECORD
